robodog/__init__.py
robodog/cli.py
sol9001_robodog-2.5.0.dist-info/METADATA
sol9001_robodog-2.5.0.dist-info/WHEEL
sol9001_robodog-2.5.0.dist-info/top_level.txt
sol9001_robodog-2.5.0.dist-info/RECORD
