Metadata-Version: 2.4
Name: sol9001-robodog
Version: 2.5.0
Summary: A short description of Robodog
Author-email: sol9001-robodog <sol9001@gmail.com>
Project-URL: Homepage, https://github.com/adourish/robodog
Project-URL: Repository, https://github.com/adourish/robodog.git
Project-URL: Documentation, https://robodog.readthedocs.io
Keywords: robot,dog,automation
Classifier: Programming Language :: Python :: 3
Classifier: License :: OSI Approved :: MIT License
Classifier: Operating System :: OS Independent
Requires-Python: >=3.7
